Workbook

Sheet Company A
A1: Company A Financial Statement | F1: Note: | G1: Company A launched it's first mobile handset leasing plans at the start of Year 1
A2: S$ Million | B2: Year 0 | C2: Year 1 | D2: Year 2 | G2: It aims to make premium handsets more affordable to customers
B3: Total | C3: Total | D3: Total
A4: Income Statement
A5: Operating revenue | B5: =B16 -> 8537 | C5: =C16 -> 9233 | D5: =D16 -> 9670
A6: Operating expenses | B6: =-B18 -> -6183.95 | C6: =-C18 -> -6269.55 | D6: =-D18 -> -6415.5
A7: EBITDA | B7: =SUM(B5:B6) -> 2353.05 | C7: =SUM(C5:C6) -> 2963.45 | D7: =SUM(D5:D6) -> 3254.5
A8: Net interest expense | B8: -130 | C8: -143 | D8: -148
A9: Taxation | B9: =-0.267*B10 -> 198.381 | C9: =-0.267*C10 -> 201.051 | D9: =-0.267*D10 -> 202.653
A10: Depreciation & amortisation | B10: -743 | C10: -753 | D10: -759
A11: Net profit | B11: =SUM(B7:B10) -> 1678.431 | C11: =SUM(C7:C10) -> 2268.501 | D11: =SUM(D7:D10) -> 2550.153
A13: Operating Revenue & Expenses Composition
A14: Mobile Service | B14: 2812 | C14: 3375 | D14: 3690
A15: Others | B15: 5725 | C15: 5858 | D15: 5980
A16: Operating revenue | B16: =SUM(B14:B15) -> 8537 | C16: =SUM(C14:C15) -> 9233 | D16: =SUM(D14:D15) -> 9670
A18: Operating expenses | B18: 6183.95 | C18: 6269.55 | D18: 6415.5
A20: Mobile Subscribers ('000s) | B20: 4085 | C20: 4195 | D20: 4409
A21: ARPU* | B21: =B14*1000/B20/12 -> 57.364341 | C21: =C14*1000/C20/12 -> 67.0441 | D21: =D14*1000/D20/12 -> 69.743706

Sheet Company B
A1: Company B Financial Statement | F1: Note: | G1: Company B operates in the same market as Company A, and has not launched leasing plans
A2: S$ Million | B2: Year 0 | C2: Year 1 | D2: Year 2
B3: Total | C3: Total | D3: Total
A4: Income Statement
A5: Operating revenue | B5: =B16 -> 8783.9 | C5: =C16 -> 9033 | D5: =D16 -> 9006.3
A6: Operating expenses | B6: =-B18 -> -6153 | C6: =-C18 -> -6372 | D6: =-D18 -> -6470
A7: EBITDA | B7: =SUM(B5:B6) -> 2630.9 | C7: =SUM(C5:C6) -> 2661 | D7: =SUM(D5:D6) -> 2536.3
A8: Net interest expense | B8: -158 | C8: -194 | D8: -189
A9: Taxation | B9: -356 | C9: -341 | D9: -304.9
A10: Depreciation & amortisation | B10: -1416 | C10: -1507 | D10: -1469
A11: Net profit | B11: =SUM(B7:B9) -> 2116.9 | C11: =SUM(C7:C9) -> 2126 | D11: =SUM(D7:D9) -> 2042.4
A13: Operating Revenue & Expenses Composition
A14: Mobile Service | B14: 5465 | C14: 5641 | D14: 5764
A15: Others | B15: 3371.2 | C15: 3363 | D15: 3101.5
A16: Operating revenue | B16: 8783.9 | C16: 9033 | D16: 9006.3
A18: Operating expenses | B18: 6153 | C18: 6372 | D18: 6470
A20: Mobile Subscribers ('000s) | B20: 9106 | C20: 9281 | D20: 9324
A21: ARPU* | B21: =B14*1000/B20/12 -> 50.012812 | C21: =C14*1000/C20/12 -> 50.650074 | D21: =D14*1000/D20/12 -> 51.515802

Sheet Comparables
A1: Growth(%) | B1: Industry Average | H1: Comparables | I1: Industry Average
B2: Year 1 | C2: Year 2 | D2: Average | E2: Comments | I2: Year 1 | J2: Year 2 | K2: Average | L2: Comments
A3: Mobile Services Revenue | B3: =('Company B'!C16+'Company A'!C16-'Company A'!B16-'Company B'!B16)/('Company B'!B16+'Company A'!B16) -> 0.054564139 | C3: =('Company B'!D16+'Company A'!D16-'Company A'!C16-'Company B'!C16)/('Company B'!C16+'Company A'!C16) -> 0.022462499 | D3: =AVERAGE(B3:C3) -> 0.038513319 | H3: Operating Revenue Growth | I3: =('Company B'!C16+'Company A'!C16-'Company A'!B16-'Company B'!B16)/('Company B'!B16+'Company A'!B16) -> 0.054564139 | J3: =('Company B'!D16+'Company A'!D16-'Company A'!C16-'Company B'!C16)/('Company B'!C16+'Company A'!C16) -> 0.022462499 | K3: =AVERAGE(I3:J3) -> 0.038513319
A4: Mobile Subscribers('000) | B4: =('Company B'!C20+'Company A'!C20-'Company B'!B20-'Company A'!B20)/('Company B'!B20+'Company A'!B20) -> 0.02160564 | C4: =('Company B'!D20+'Company A'!D20-'Company B'!C20-'Company A'!C20)/('Company B'!C20+'Company A'!C20) -> 0.019070941 | D4: =AVERAGE(B4:C4) -> 0.020338291 | E4: Overall industry for mobile subscribers is growing at 2.03% on average. | H4: Net Profit Growth | I4: =('Company B'!C11+'Company A'!C11-'Company B'!B11-'Company A'!B11)/('Company B'!B11+'Company A'!B11) -> 0.15787029 | J4: =('Company B'!D11+'Company A'!D11-'Company B'!C11-'Company A'!C11)/('Company B'!C11+'Company A'!C11) -> 0.045068143 | K4: =AVERAGE(I4:J4) -> 0.10146922
H5: ARPU* | I5: =('Company B'!C14+'Company A'!C14)/('Company A'!C20+'Company B'!C20)*1000/12 -> 55.753438 | J5: =('Company B'!D14+'Company A'!D14)/('Company A'!D20+'Company B'!D20)*1000/12 -> 57.367897 | K5: =AVERAGE(I5:J5) -> 56.560668
H6: *Average Revenue Per User
A7: Growth(%) | B7: Company A
B8: Year 1 | C8: Year 2 | D8: Average | E8: Comments
A9: Mobile Services Revenue | B9: =('Company A'!C16+'Company A'!C16-'Company A'!B16-'Company A'!B16)/('Company A'!B16+'Company A'!B16) -> 0.081527469 | C9: =('Company A'!D16+'Company A'!D16-'Company A'!C16-'Company A'!C16)/('Company A'!C16+'Company A'!C16) -> 0.047330229 | D9: =AVERAGE(B9:C9) -> 0.064428849
A10: Mobile Subscribers('000) | B10: =('Company A'!C20+'Company A'!C20-'Company A'!B20-'Company A'!B20)/('Company A'!B20+'Company A'!B20) -> 0.026927785 | C10: =('Company A'!D20+'Company A'!D20-'Company A'!C20-'Company A'!C20)/('Company A'!C20+'Company A'!C20) -> 0.051013111 | D10: =AVERAGE(B10:C10) -> 0.038970448 | H10: Market Share (%) | I10: Company A
I11: Year 0 | J11: Year 1 | K11: Year 2 | L11: Average | M11: Comments
H12: Mobile Service | I12: ='Company A'!B14/('Company A'!B14+'Company B'!B14) -> 0.33973662 | J12: ='Company A'!C14/('Company A'!C14+'Company B'!C14) -> 0.37433452 | K12: ='Company A'!D14/('Company A'!D14+'Company B'!D14) -> 0.39031098 | L12: =AVERAGE(I12:K12) -> 0.36812737
B13: Year 1 | C13: Year 2 | D13: Average | E13: Comments | H13: ARPU* | I13: =('Company A'!B14/'Company A'!B20)*1000/12 -> 57.364341 | J13: =('Company A'!C14/'Company A'!C20)*1000/12 -> 67.0441 | K13: =('Company A'!D14/'Company A'!D20)*1000/12 -> 69.743706 | L13: =AVERAGE(I13:K13) -> 64.717382 | M13: Higher growth in ARPU than Company B
A14: Mobile Services Revenue | B14: =('Company B'!C16+'Company B'!C16-'Company B'!B16-'Company B'!B16)/('Company B'!B16+'Company B'!B16) -> 0.028358702 | C14: =('Company B'!D16+'Company B'!D16-'Company B'!C16-'Company B'!C16)/('Company B'!C16+'Company B'!C16) -> -0.0029558286 | D14: =AVERAGE(B14:C14) -> 0.012701437 | E14: Company B grows 2.58% below average,likely due to no leasing.
A15: Mobile Subscribers('000) | B15: =('Company B'!C20+'Company B'!C20-'Company B'!B20-'Company B'!B20)/('Company B'!B20+'Company B'!B20) -> 0.019218098 | C15: =('Company B'!D20+'Company B'!D20-'Company B'!C20-'Company B'!C20)/('Company B'!C20+'Company B'!C20) -> 0.0046331214 | D15: =AVERAGE(B15:C15) -> 0.01192561
H16: Market Share (%) | I16: Company A
I17: Year 0 | J17: Year 1 | K17: Year 2 | L17: Average | M17: Comments
H18: Mobile Service | I18: ='Company B'!B14/('Company B'!B14+'Company A'!B14) -> 0.66026338 | J18: ='Company B'!C14/('Company B'!C14+'Company A'!C14) -> 0.62566548 | K18: ='Company B'!D14/('Company B'!D14+'Company A'!D14) -> 0.60968902 | L18: =AVERAGE(I18:K18) -> 0.63187263 | M18: Decrease in market share again,due to no leasing option
H19: ARPU* | I19: =('Company B'!B14/'Company B'!B20)*1000/12 -> 50.012812 | J19: =('Company B'!C14/'Company B'!C20)*1000/12 -> 50.650074 | K19: =('Company B'!D14/'Company B'!D20)*1000/12 -> 51.515802 | L19: =AVERAGE(I19:K19) -> 50.726229 | M19: Lower growth od ARPU than Company A

Sheet Guiding Sheet
A1: Guiding Sheet
A3: What are the key steps you need to arrive at the answer?
A4: You are trying to find the incremental impact of introducing handset leasing. To do this, you need to estimate what happens if you introduce leasing vs do not introduce leasing.
A6: 5 steps to solving this task
A7: Step 1. Identify the metrics that are most important
A8: Step 2. To estimate the no leasing case, you apply the industry average growth rates for the relevant metrics for Company X
A9: Step 3. To estimate the leasing case, you apply Company A growth rates
A10: Step 4. Make logical estimates for all other figures, using historical data
A11: Step 5. Calculate the impact of handset leasing for Company X
A14: Step 1. Identify the metrics that are most important
A15: 1a. Net profit | B15: Ultimately the most important number, but it is a dependant variable, and hence will need to be calculated
A16: 1b. Operating Revenue | B16: This is the biggest driver of net profit as most other aspects remain constant
A17: 1c. ARPU | B17: As an additional measure of performance
A20: Step 2. To estimate the no leasing case, you apply the industry average growth rates for the relevant metrics for Company X
A21: 2a. Estimate industry average growth rates by combining the data for Company A and Company B for the key metrics
A22: 2b. Apply the industry average to forecast Company X performance if handset leasing is not introduced
A25: Step 3. To estimate the leasing case, you apply Company A growth rates to Company X
A28: Step 4. Make logical estimates for all other figures, using historical data
A29: 4a. Some metrics are likely to be a fixed ratio of revenue or profits
A30: 4b. For others, the best estimate is just to assume it will remain constant
A33: Step 5. Calculate the impact of handset leasing for Company X
A34: 5a. To show the difference in Company X's key metrics with and without handset leasing, you subtract the numbers in step (2) from step (3) and (4)

Sheet Company X
A5: Company X Financial Statement (handset leasing implemented) | G5: Company X Financial Statement (handset leasing not implemented) | M5: Difference in Company X Financial Statement with and without handset leasing
A6: S$ Million | B6: Year 0 | C6: Year 1 | D6: Year 2 | E6: Comments | G6: S$ Million | H6: Year 0 | I6: Year 1 | J6: Year 2 | K6: Comments | M6: S$ Million | N6: Year 0 | O6: Year 1 | P6: Year 2 | Q6: Comment
B7: Total | C7: Total | D7: Total | H7: Total | I7: Total | J7: Total | N7: Total | O7: Total | P7: Total
A8: Income Statement | G8: Income Statement | M8: Income Statement
A9: Operating revenue | B9: 2362 | C9: =C21 -> 2449.2367 | D9: =D21 -> 2542.0939 | G9: Operating revenue | H9: 2362 | I9: =I21 -> 2414.147 | J9: =J21 -> 2468.3024 | M9: Operating revenue | N9: =B9-H9 -> 0 | O9: =C9-I9 -> 35.089627 | P9: =D9-J9 -> 73.791457
A10: Operating expenses | B10: -1795.9 | C10: =-C24 -> -1862.3324 | D10: =-D24 -> -1932.9384 | G10: Operating expenses | H10: -1795.9 | I10: =-I24 -> -1835.6512 | J10: =-J24 -> -1876.8294 | M10: Operating expenses | N10: =B10-H10 -> 0 | O10: =C10-I10 -> -26.68119 | P10: =D10-J10 -> -56.108999
A11: EBITDA | B11: =SUM(B9:B10) -> 566.1 | C11: =SUM(C9:C10) -> 586.9043 | D11: =SUM(D9:D10) -> 609.15543 | G11: EBITDA | H11: =SUM(H9:H10) -> 566.1 | I11: =SUM(I9:I10) -> 578.49586 | J11: =SUM(J9:J10) -> 591.47298 | M11: EBITDA | N11: =B11-H11 -> 0 | O11: =C11-I11 -> 8.4084373 | P11: =D11-J11 -> 17.682457
A12: Net finance expense | B12: -27 | C12: -27 | D12: -27 | G12: Net finance expense | H12: -27 | I12: -27 | J12: -27 | M12: Net finance expense | N12: =B12-H12 -> 0 | O12: =C12-I12 -> 0 | P12: =D12-J12 -> 0
A13: Taxation | B13: -44.9 | C13: -44.9 | D13: -44.9 | G13: Taxation | H13: -44.9 | I13: -44.9 | J13: -44.9 | M13: Taxation | N13: =B13-H13 -> 0 | O13: =C13-I13 -> 0 | P13: =D13-J13 -> 0
A14: Depreciation & amortisation | B14: -293.8 | C14: -293.8 | D14: -293.8 | G14: Depreciation & amortisation | H14: -293.8 | I14: -293.8 | J14: -293.8 | M14: Depreciation & amortisation | N14: =B14-H14 -> 0 | O14: =C14-I14 -> 0 | P14: =D14-J14 -> 0
A15: Net profit | B15: =SUM(B11:B14) -> 200.4 | C15: =SUM(C11:C14) -> 221.2043 | D15: =SUM(D11:D14) -> 243.45543 | G15: Net profit | H15: =SUM(H11:H14) -> 200.4 | I15: =SUM(I11:I14) -> 212.79586 | J15: =SUM(J11:J14) -> 225.77298 | M15: Net profit | N15: =B15-H15 -> 0 | O15: =C15-I15 -> 8.4084373 | P15: =D15-J15 -> 17.682457
A16: Growth Rate | C16: =(C15-B15)/B15 -> 0.10381386 | D16: =(D15-C15)/C15 -> 0.10059089 | E16: Average growth rate is 10.22%.0.07% higher than the industry average | G16: Growth rate | I16: =(I15-H15)/H15 -> 0.061855588 | J16: =(J15-I15)/I15 -> 0.060983879 | K16: Net profit Growth of 6.145% is lower than industry average of 10.15% | M16: Growth rate | O16: =C16-I16 -> 0.04195827 | P16: =D16-J16 -> 0.039607011 | Q16: Difference of 4.08% growth rate in profits
A18: Operating Revenue & Expenses Composition | G18: Operating Revenue & Expenses Composition | M18: Operating Revenue & Expenses Composition
A19: Mobile Service | B19: 1354 | C19: =B19*(Comparables!$D$9+1) -> 1441.2367 | D19: =C19*(Comparables!$D$9+1) -> 1534.0939 | E19: Assume growth 6.44% | G19: Mobile Service | H19: 1354 | I19: =H19*(Comparables!D3+1) -> 1406.147 | J19: =I19*(Comparables!D3+1) -> 1460.3024 | K19: Assume 3.85% growth i.e, industry average | M19: Mobile Service | N19: 1354 | O19: =C19-I19 -> 35.089627 | P19: =D19-J19 -> 73.791457
A20: Others | B20: 1008 | C20: 1008 | D20: 1008 | E20: Assume constant | G20: Others | H20: 1008 | I20: 1008 | J20: 1008 | M20: Others | N20: 1008 | O20: =C20-I20 -> 0 | P20: =D20-J20 -> 0
A21: Operating revenue | B21: =SUM(B19:B20) -> 2362 | C21: =SUM(C19:C20) -> 2449.2367 | D21: =SUM(D19:D20) -> 2542.0939 | G21: Operating revenue | H21: =SUM(H19:H20) -> 2362 | I21: =SUM(I19:I20) -> 2414.147 | J21: =SUM(J19:J20) -> 2468.3024 | M21: Operating revenue | N21: =SUM(N19:N20) -> 2362 | O21: =C21-I21 -> 35.089627 | P21: =D21-J21 -> 73.791457
A22: Growth Rate | C22: =(C21-B21)/B21 -> 0.036933387 | D22: =(D21-C21)/C21 -> 0.037912718 | G22: Growth rate | I22: =(I21-H21)/H21 -> 0.022077491 | J22: =(J21-I21)/I21 -> 0.022432515 | K22: Grwoth of 2.22% is 1.53% below industry average of 3.85% | M22: Growth rate | O22: =C22-I22 -> 0.014855896 | P22: =D22-J22 -> 0.015480203 | Q22: 1.5% difference in operating revenue with handset leasing
A24: Operating expenses | B24: 1796 | C24: =(1796/2362)*C21 -> 1862.3324 | D24: =(1796/2362)*D21 -> 1932.9384 | E24: Assume constant expense ratio | G24: Operating expenses | H24: 1796 | I24: =(1796/2362)*I21 -> 1835.6512 | J24: =(1796/2362)*J21 -> 1876.8294 | M24: Operating expenses | N24: 1796 | O24: =C24-I24 -> 26.68119 | P24: =D24-J24 -> 56.108999
A26: Mobile Subscribers ('000s) | B26: 2341 | C26: =B26*(Comparables!D10+1) -> 2432.2298 | D26: =C26*(Comparables!D10+1) -> 2527.0149 | E26: Assume 3.90% growth | G26: Mobile Subscribers ('000s) | H26: 2341 | I26: =H26*(Comparables!D4+1) -> 2388.6119 | J26: =I26*(Comparables!D4+1) -> 2437.1922 | M26: Mobile Subscribers ('000s) | N26: =B26-H26 -> 0 | O26: =C26-I26 -> 43.61788 | P26: =D26-J26 -> 89.822681
A27: ARPU* | B27: =B19*1000/B26/12 -> 48.198775 | C27: =C19*1000/C26/12 -> 49.379814 | D27: =D19*1000/D26/12 -> 50.589791 | E27: ARPU is below industry average $56.56 however, it reflects positive growth | G27: ARPU* | H27: =H19*1000/H26/12 -> 48.198775 | I27: =I19*1000/I26/12 -> 49.057328 | J27: =J19*1000/J26/12 -> 49.931174 | K27: No leasing leads to significally lower ARPU | M27: ARPU* | N27: =B27-H27 -> 0 | O27: =C27-I27 -> 0.32248554 | P27: =D27-J27 -> 0.65861746 | Q27: $1 difference by year 2
